cli/README.md
cli/__init__.py
cli/__main__.py
cli/expressions.py
cli/sharing.py
cli/testing/create_table_test.toml
cli/testing/ingest_feature_list.json
cli/testing/list_features_test.json
descarteslabs/vector/__init__.py
descarteslabs/vector/common.py
descarteslabs/vector/features.py
descarteslabs/vector/layers.py
descarteslabs/vector/models.py
descarteslabs/vector/products.py
descarteslabs/vector/tiles.py
descarteslabs/vector/util.py
descarteslabs/vector/vector.py
descarteslabs/vector/vector_exceptions.py
descarteslabs_vector-0.2.0.dist-info/LICENSE
descarteslabs_vector-0.2.0.dist-info/METADATA
descarteslabs_vector-0.2.0.dist-info/WHEEL
descarteslabs_vector-0.2.0.dist-info/entry_points.txt
descarteslabs_vector-0.2.0.dist-info/RECORD
