Metadata-Version: 2.1
Name: descarteslabs-vector
Version: 0.2.0
Summary: 
License: Apache-2.0
Author: Descartes Labs
Requires-Python: >=3.8,<3.12
Classifier: License :: OSI Approved :: Apache Software License
Classifier: Programming Language :: Python :: 3
Classifier: Programming Language :: Python :: 3.8
Classifier: Programming Language :: Python :: 3.9
Classifier: Programming Language :: Python :: 3.10
Classifier: Programming Language :: Python :: 3.11
Requires-Dist: backoff (>=2.2.1,<3.0.0)
Requires-Dist: click (>=8.1.3,<9.0.0)
Requires-Dist: descarteslabs (>=2,<3)
Requires-Dist: geopandas (>=0.13.2,<0.14.0)
Requires-Dist: ipyleaflet (>=0.17.2,<0.18.0)
Requires-Dist: pyarrow (>=13.0.0,<14.0.0)
Requires-Dist: pydantic (>=2.1.1,<3.0.0)
Requires-Dist: toml (>=0.10.2,<0.11.0)
Requires-Dist: urllib3 (==1.26.17)
